halo_analysis/__init__.py
halo_analysis/halo_default.py
halo_analysis/halo_io.py
halo_analysis/halo_plot.py
halo_analysis/halo_select.py
halo_analysis-1.0.4.dist-info/licenses/LICENSE.md
halo_analysis-1.0.4.dist-info/METADATA
halo_analysis-1.0.4.dist-info/WHEEL
halo_analysis-1.0.4.dist-info/top_level.txt
halo_analysis-1.0.4.dist-info/RECORD
