Metadata-Version: 2.4
Name: halo_analysis
Version: 1.0.4
Summary: read and analyze halo/galaxy catalogs
Author: Andrew Wetzel, Shea Garrison-Kimmel, Zach Hafen, Nico Garavito-Camargo, Kyle Oman
Maintainer-email: Andrew Wetzel <arwetzel@gmail.com>
License: Copyright 2014-2024 by the authors.
Project-URL: Repository, https://bitbucket.org/awetzel/halo_analysis/src/master/
Project-URL: Issues, https://bitbucket.org/awetzel/halo_analysis/issues?status=new&status=open&status=submitted
Keywords: gizmo,astronomy,astrophysics,cosmology,galaxies,stars,dark matter
Classifier: Programming Language :: Python :: 3
Classifier: License :: OSI Approved :: MIT License
Classifier: Topic :: Scientific/Engineering :: Astronomy
Classifier: Development Status :: 4 - Beta
Classifier: Operating System :: OS Independent
Requires-Python: >=3.10
License-File: LICENSE.md
Requires-Dist: numpy>=1.23
Requires-Dist: scipy>=1.13
Requires-Dist: h5py>=3.9
Requires-Dist: matplotlib>=3.9
Requires-Dist: utilities-awetzel>=1.0.3
Dynamic: license-file
